[
  {
    "id": "2018-12-25T12:54:36.269Z",
    "key": "2018-12-25T12:54:36.269Z",
    "value": {
      "rev": "1-cbe4d05a0f4a516f1b0d18bbd63650a0"
    },
    "doc": {
      "lastName": "Набережный",
      "firstName": "Виталий",
      "middleName": "Викторович",
      "address": "г Сыктывкар, ул Кутузова, д 17",
      "phone": "+7 (912) 864-94-11",
      "email": "vvnab@mail.ru",
      "social": "https://vk.com/vvnab",
      "helper": [
        "Готов помочь с разовыми поручениями"
      ],
      "privacy": true,
      "_id": "2018-12-25T12:54:36.269Z",
      "_rev": "1-cbe4d05a0f4a516f1b0d18bbd63650a0"
    }
  },
  {
    "id": "2018-12-26T03:11:54.984Z",
    "key": "2018-12-26T03:11:54.984Z",
    "value": {
      "rev": "1-d4c3c601ac4974ef1389c0c2052b4b3b"
    },
    "doc": {
      "lastName": "Нефедьев",
      "firstName": "Алексей",
      "address": "гСыктывкар",
      "phone": "+7 (904) 270-73-33",
      "helper": [
        "Я адвокат",
        "Я журналист / у меня есть личный блог",
        "У меня есть личный транспорт",
        "Я могу помочь с обзвоном волонтеров",
        "Я эколог",
        "Готов помочь с разовыми поручениями"
      ],
      "email": "taxi-099@mail.ru",
      "social": "https://vk.com/zacistijkrai",
      "privacy": true,
      "_id": "2018-12-26T03:11:54.984Z",
      "_rev": "1-d4c3c601ac4974ef1389c0c2052b4b3b"
    }
  },
  {
    "id": "2018-12-26T04:35:23.486Z",
    "key": "2018-12-26T04:35:23.486Z",
    "value": {
      "rev": "1-9dd94c93cd98ac2e840a1c42242bbf31"
    },
    "doc": {
      "lastName": "Денич",
      "firstName": "Сергей",
      "middleName": "Владимирович",
      "address": "респ Коми, г Ухта, ко Интернациональная, д 11",
      "phone": "+7 (911) 972-05-15",
      "email": "DenisovS.V.LSEG@yandex.ru",
      "privacy": true,
      "social": "https://vk.com/id54164418",
      "_id": "2018-12-26T04:35:23.486Z",
      "_rev": "1-9dd94c93cd98ac2e840a1c42242bbf31"
    }
  },
  {
    "id": "2018-12-26T05:43:37.072Z",
    "key": "2018-12-26T05:43:37.072Z",
    "value": {
      "rev": "1-68db51e2fd4cf82663e366069c76cf77"
    },
    "doc": {
      "lastName": "Кораблева",
      "firstName": "Наталья",
      "middleName": "Николаевна",
      "address": "г Сыктывкар, ул Свободы, д 29",
      "phone": "+7 (912) 863-90-83",
      "email": "kemcard@yandex.ru",
      "helper": [
        "Готов помочь с разовыми поручениями"
      ],
      "privacy": true,
      "social": "https://vk.com/id4559722",
      "_id": "2018-12-26T05:43:37.072Z",
      "_rev": "1-68db51e2fd4cf82663e366069c76cf77"
    }
  },
  {
    "id": "2018-12-26T14:58:53.342Z",
    "key": "2018-12-26T14:58:53.342Z",
    "value": {
      "rev": "1-3a04760cd27ffc2a1b12398670356659"
    },
    "doc": {
      "lastName": "Зотикова",
      "firstName": "Мария ",
      "middleName": "Федоровна",
      "address": "СПб, Парголово, БАйкальская, 58",
      "phone": "+7 (931) 210-28-64",
      "email": "masha-zotikova@yandex.ru",
      "helper": [
        "Готов помочь с разовыми поручениями"
      ],
      "privacy": true,
      "social": "https://vk.com/id199955065",
      "_id": "2018-12-26T14:58:53.342Z",
      "_rev": "1-3a04760cd27ffc2a1b12398670356659"
    }
  },
  {
    "id": "2018-12-26T21:09:37.845Z",
    "key": "2018-12-26T21:09:37.845Z",
    "value": {
      "rev": "1-e2b72634133726a605055b921fd41d2e"
    },
    "doc": {
      "lastName": "Гавриленко",
      "firstName": "Артём",
      "middleName": "Николаевич",
      "address": "г. Ростов-на-Дону, ул. Малиновского",
      "phone": "+7 (928) 601-23-60",
      "email": "gavart-de@yandex.ru",
      "social": "https://vk.com/artstrong",
      "helper": [
        "Готов помочь с разовыми поручениями"
      ],
      "privacy": true,
      "_id": "2018-12-26T21:09:37.845Z",
      "_rev": "1-e2b72634133726a605055b921fd41d2e"
    }
  },
  {
    "id": "2018-12-27T08:10:45.231Z",
    "key": "2018-12-27T08:10:45.231Z",
    "value": {
      "rev": "1-437833b303b46b8b9584dec29ca46255"
    },
    "doc": {
      "privacy": true,
      "helper": [
        "Готов помочь с разовыми поручениями"
      ],
      "lastName": "Синюшкин",
      "firstName": "Евгений",
      "middleName": "Сергеевич",
      "address": "Архангельская обл, г Котлас",
      "phone": "+7 (895) 230-01-35",
      "email": "dgonii789@yandex.ru",
      "social": "https://vk.com/id372716371",
      "_id": "2018-12-27T08:10:45.231Z",
      "_rev": "1-437833b303b46b8b9584dec29ca46255"
    }
  },
  {
    "id": "2018-12-27T09:00:11.225Z",
    "key": "2018-12-27T09:00:11.225Z",
    "value": {
      "rev": "1-5b0b617c34ab511853937312950c810a"
    },
    "doc": {
      "social": "https://m.vk.com/id2668056",
      "email": "temkina06@mail.ru",
      "phone": "+7 (911) 584-94-65",
      "address": "г Архангельск, ул Урицкого, д 2.",
      "middleName": "Николаевна ",
      "firstName": "Юлия ",
      "lastName": "Княжук ",
      "helper": [
        "Я могу помочь с обзвоном волонтеров",
        "Готов помочь с разовыми поручениями",
        "У меня есть личный транспорт"
      ],
      "privacy": true,
      "_id": "2018-12-27T09:00:11.225Z",
      "_rev": "1-5b0b617c34ab511853937312950c810a"
    }
  },
  {
    "id": "2018-12-27T12:53:39.760Z",
    "key": "2018-12-27T12:53:39.760Z",
    "value": {
      "rev": "1-5e86516ddbe80d02617047e9772b7e1c"
    },
    "doc": {
      "lastName": "Шахова ",
      "firstName": "Наталья ",
      "middleName": "Николаевна",
      "address": "Архангельская обл, г Северодвинск, Архангельское шоссе, д 81 ",
      "phone": "+7 (921) 482-40-85",
      "email": "androgen37048112@yandex.ru",
      "social": "https://vk.com/natalyashakhova374",
      "helper": [
        "Готов помочь с разовыми поручениями"
      ],
      "privacy": true,
      "_id": "2018-12-27T12:53:39.760Z",
      "_rev": "1-5e86516ddbe80d02617047e9772b7e1c"
    }
  },
  {
    "id": "2018-12-28T09:16:45.167Z",
    "key": "2018-12-28T09:16:45.167Z",
    "value": {
      "rev": "1-cbc4fb87cd28a7f6d742b3ed6aa7ce90"
    },
    "doc": {
      "lastName": "Пронина",
      "firstName": "Екатерина ",
      "middleName": "Алексеевна ",
      "address": "Г. Новодвинск, ул Солнечная 5",
      "phone": "+7 (891) 159-89-19",
      "email": "pon-katya@yandex.ru",
      "social": "https://vk.com/pronina_ekaterina",
      "privacy": true,
      "_id": "2018-12-28T09:16:45.167Z",
      "_rev": "1-cbc4fb87cd28a7f6d742b3ed6aa7ce90"
    }
  },
  {
    "id": "2018-12-28T11:57:22.623Z",
    "key": "2018-12-28T11:57:22.623Z",
    "value": {
      "rev": "1-23f0a1cd5bc5709bd19824a5b058449c"
    },
    "doc": {
      "lastName": "Бабяк",
      "firstName": "Татьяна",
      "middleName": "Вениаминовна",
      "address": "Архангельская область Ленский район п. Очея улица Черёмушки , д 6 ",
      "phone": "+7 (818) 597-81-78",
      "email": "babyak.tatyana.2017@mail.ru",
      "privacy": true,
      "social": "https://vk.com/id375000758",
      "_id": "2018-12-28T11:57:22.623Z",
      "_rev": "1-23f0a1cd5bc5709bd19824a5b058449c"
    }
  },
  {
    "id": "2018-12-28T17:00:03.369Z",
    "key": "2018-12-28T17:00:03.369Z",
    "value": {
      "rev": "1-3b3c8b5cf9709c861e767096306ef3ba"
    },
    "doc": {
      "lastName": "Ромицын",
      "firstName": "Владимир",
      "middleName": "Альбертович",
      "address": "Архангельская обл, Вельский р-н, рп Кулой, ул Комсомольская, д 54А, кв 31",
      "phone": "+7 (921) 081-10-70",
      "social": "volodya.romicin@gmail.com",
      "helper": [
        "У меня есть личный транспорт",
        "Я могу помочь с обзвоном волонтеров",
        "Готов помочь с разовыми поручениями"
      ],
      "privacy": true,
      "email": "volodya.romicin@gmail.com",
      "_id": "2018-12-28T17:00:03.369Z",
      "_rev": "1-3b3c8b5cf9709c861e767096306ef3ba"
    }
  },
  {
    "id": "2018-12-28T18:26:14.825Z",
    "key": "2018-12-28T18:26:14.825Z",
    "value": {
      "rev": "1-e66353ddd5dc6de5aa73821d028138e2"
    },
    "doc": {
      "helper": [
        "Готов помочь с разовыми поручениями",
        "Я могу помочь с обзвоном волонтеров"
      ],
      "privacy": true,
      "lastName": "Семенова",
      "firstName": "Ульяна",
      "middleName": "Игоревна",
      "address": "Московская обл, г Дзержинский, ул Строителей, д 14",
      "phone": "+7 (967) 179-85-81",
      "email": "decatria13@gmail.com",
      "social": "https://vk.com/decatria",
      "_id": "2018-12-28T18:26:14.825Z",
      "_rev": "1-e66353ddd5dc6de5aa73821d028138e2"
    }
  },
  {
    "id": "2018-12-28T19:38:22.389Z",
    "key": "2018-12-28T19:38:22.389Z",
    "value": {
      "rev": "1-add5341651a9a8cd301d677d8abbb79f"
    },
    "doc": {
      "lastName": "Савельев",
      "firstName": "Пётр Николаевич",
      "address": "ул. Комсомольская д.11",
      "email": "mixus7@mail.ru",
      "helper": [
        "Готов помочь с разовыми поручениями",
        "Я могу помочь с обзвоном волонтеров"
      ],
      "privacy": true,
      "phone": "+7 (953) 933-09-50",
      "social": "mixus7@mail.ru",
      "middleName": "Николаевич",
      "_id": "2018-12-28T19:38:22.389Z",
      "_rev": "1-add5341651a9a8cd301d677d8abbb79f"
    }
  },
  {
    "id": "2018-12-28T22:25:52.453Z",
    "key": "2018-12-28T22:25:52.453Z",
    "value": {
      "rev": "1-7ce545f9a530350b9a5ff48fe5efeb1b"
    },
    "doc": {
      "social": "https://vk.com/id424834057",
      "email": "kononova_ni@mail.ru",
      "phone": "+7 (916) 870-74-75",
      "address": "Московская обл, Одинцовский р-н, поселок Новый Городок",
      "middleName": "Ивановна",
      "firstName": "Наталья",
      "lastName": "Кононова",
      "privacy": true,
      "helper": [
        "Готов помочь с разовыми поручениями"
      ],
      "_id": "2018-12-28T22:25:52.453Z",
      "_rev": "1-7ce545f9a530350b9a5ff48fe5efeb1b"
    }
  },
  {
    "id": "2018-12-29T12:37:20.486Z",
    "key": "2018-12-29T12:37:20.486Z",
    "value": {
      "rev": "1-76fa95d9f18fb551edd1348e4b749afc"
    },
    "doc": {
      "helper": [
        "У меня есть личный транспорт"
      ],
      "privacy": true,
      "lastName": "Крылова ",
      "firstName": "Ирина ",
      "middleName": "Валерьевна ",
      "address": "г Архангельск, ул Воскресенская",
      "phone": "+7 (952) 250-91-71",
      "email": "iriya11@ya.ru",
      "social": "https://vk.com/id23261703",
      "_id": "2018-12-29T12:37:20.486Z",
      "_rev": "1-76fa95d9f18fb551edd1348e4b749afc"
    }
  },
  {
    "id": "2019-01-03T02:29:51.638Z",
    "key": "2019-01-03T02:29:51.638Z",
    "value": {
      "rev": "1-c9b82e712aa1e79aafc1e8ed5319a56e"
    },
    "doc": {
      "social": "https://vk.com/idmaksimkapussshot",
      "lastName": "Пушкин",
      "firstName": "Максим",
      "middleName": "Сергеевич",
      "address": "г Архангельск, ул Пионерская, д 154",
      "phone": "+7 (996) 920-62-15",
      "email": "puschkin.maxim2017@yandex.ru",
      "helper": [
        "Готов помочь с разовыми поручениями"
      ],
      "privacy": true,
      "_id": "2019-01-03T02:29:51.638Z",
      "_rev": "1-c9b82e712aa1e79aafc1e8ed5319a56e"
    }
  },
  {
    "id": "2019-01-04T09:41:43.681Z",
    "key": "2019-01-04T09:41:43.681Z",
    "value": {
      "rev": "1-6fabd4cc41e43f8b9dd111fea7941f33"
    },
    "doc": {
      "social": "https://www.facebook.com/profile.php?id=1663103282",
      "lastName": "Боровинский",
      "firstName": "Александр",
      "middleName": "Юрьевич",
      "address": "Ухта, Авиационная 2",
      "phone": "+7 (912) 505-51-61",
      "email": "aborovinsky@list.ru",
      "helper": [
        "У меня есть личный транспорт"
      ],
      "privacy": true,
      "_id": "2019-01-04T09:41:43.681Z",
      "_rev": "1-6fabd4cc41e43f8b9dd111fea7941f33"
    }
  },
  {
    "id": "2019-01-04T19:10:17.527Z",
    "key": "2019-01-04T19:10:17.527Z",
    "value": {
      "rev": "1-89f939b3263db56fbd9b165fdf6b3ff3"
    },
    "doc": {
      "lastName": "Нурисламов",
      "firstName": "Эдуард",
      "middleName": "Ринатович",
      "address": "респ Татарстан, Высокогорский р-н, село Высокая Гора",
      "email": "ednur@yandex.ru",
      "phone": "+7 (917) 914-17-01",
      "privacy": true,
      "social": "https://vk.com/id505781235",
      "_id": "2019-01-04T19:10:17.527Z",
      "_rev": "1-89f939b3263db56fbd9b165fdf6b3ff3"
    }
  },
  {
    "id": "2019-01-05T18:28:27.593Z",
    "key": "2019-01-05T18:28:27.593Z",
    "value": {
      "rev": "1-9477f4528531b06bfcb8ef57d288b69e"
    },
    "doc": {
      "lastName": "Поздеев",
      "firstName": "Роман",
      "middleName": "Павлович",
      "address": "Архангельская обл, г Котлас, ул 28 Невельской дивизии, д 4",
      "phone": "+7 (921) 290-98-90",
      "privacy": true,
      "helper": [
        "Готов помочь с разовыми поручениями"
      ],
      "email": "Rom15276019@yandex.ru",
      "social": "Rom15276019@yandex.ru",
      "_id": "2019-01-05T18:28:27.593Z",
      "_rev": "1-9477f4528531b06bfcb8ef57d288b69e"
    }
  },
  {
    "id": "2019-01-05T21:42:26.748Z",
    "key": "2019-01-05T21:42:26.748Z",
    "value": {
      "rev": "1-7d9b320061ad2f21d40c1706d6fa4895"
    },
    "doc": {
      "lastName": "Лебедева",
      "firstName": "Наталья",
      "middleName": "Владимировна",
      "address": "Архангельская обл, г Северодвинск, ул Юбилейная, д 29",
      "email": "25nata08@mail.ru",
      "phone": "+7 (952) 254-95-96",
      "privacy": true,
      "social": "http://vk.com/id104185819",
      "_id": "2019-01-05T21:42:26.748Z",
      "_rev": "1-7d9b320061ad2f21d40c1706d6fa4895"
    }
  }
]